[
    {
        "251017": [
            "Neexistuje",
            "Neexistuje",
            "Neexistuje",
            "-",
            "Neexistuje",
            "Neexistuje",
            "Neexistuje"
        ],
        "251024": [
            "Neexistuje",
            "Neexistuje",
            "Neexistuje",
            "-",
            "Neexistuje",
            "Neexistuje",
            "Neexistuje"
        ],
        "251012": [
            -20,
            -15,
            -7,
            "-",
            0.75,
            0.66,
            0.62
        ],
        "251013": [
            "Neexistuje",
            "Neexistuje",
            -2,
            "-",
            0.95,
            "Neexistuje",
            "Neexistuje"
        ],
        "251014": [
            -5,
            -2,
            -1,
            "-",
            0.98,
            0.97,
            0.95
        ]
    },
    {
        "251017": [
            {
                "symbol": "109000-C",
                "markPrice": "4531.2",
                "bidIV": "0.5083847",
                "askIV": "0.52729487",
                "markIV": "0.5186",
                "delta": "0.67100314",
                "theta": "-231.20673354",
                "gamma": "0.00005028",
                "vega": "50.25095358",
                "highPriceLimit": "17782.9",
                "lowPriceLimit": "5",
                "riskFreeInterest": "0.01877188"
            },
            {
                "symbol": "110000-C",
                "markPrice": "3862.1",
                "bidIV": "0.49669862",
                "askIV": "0.51560998",
                "markIV": "0.5094",
                "delta": "0.61987119",
                "theta": "-237.9160494",
                "gamma": "0.00005415",
                "vega": "52.90286152",
                "highPriceLimit": "19173.4",
                "lowPriceLimit": "5",
                "riskFreeInterest": "0.01877188"
            },
            {
                "symbol": "111000-C",
                "delta": 0
            },
            {
                "symbol": "112000-C",
                "markPrice": "2629.9",
                "bidIV": "0.48163652",
                "askIV": "0.49336672",
                "markIV": "0.48163652",
                "delta": "0.50713764",
                "theta": "-240.03000104",
                "gamma": "0.00005889",
                "vega": "55.41528903",
                "highPriceLimit": "22348.6",
                "lowPriceLimit": "5",
                "riskFreeInterest": "0.01877188"
            },
            {
                "symbol": "113000-C",
                "markPrice": "2154.9",
                "bidIV": "0.47774673",
                "askIV": "0.48047721",
                "markIV": "0.47774673",
                "delta": "0.44737574",
                "theta": "-233.88178317",
                "gamma": "0.00005941",
                "vega": "54.94114791",
                "highPriceLimit": "22938.3",
                "lowPriceLimit": "5",
                "riskFreeInterest": "0.01877188"
            },
            {
                "symbol": "114000-C",
                "markPrice": "1738.3",
                "bidIV": "0.47025204",
                "askIV": "0.47682643",
                "markIV": "0.4737",
                "delta": "0.38831133",
                "theta": "-223.99341734",
                "gamma": "0.00005825",
                "vega": "53.23760821",
                "highPriceLimit": "23275",
                "lowPriceLimit": "5",
                "riskFreeInterest": "0.01877188"
            },
            {
                "symbol": "115000-C",
                "delta": 0
            }
        ],
        "251024": [
            {
                "symbol": "109000-C",
                "markPrice": "5423.6",
                "bidIV": "0.45367002",
                "askIV": "0.48949599",
                "markIV": "0.4612",
                "delta": "0.63785189",
                "theta": "-145.6537662",
                "gamma": "0.00003821",
                "vega": "78.00129033",
                "highPriceLimit": "20008",
                "lowPriceLimit": "5",
                "riskFreeInterest": "0.01791065"
            },
            {
                "symbol": "110000-C",
                "markPrice": "4799.9",
                "bidIV": "0.45659304",
                "askIV": "0.46962976",
                "markIV": "0.45659304",
                "delta": "0.59772311",
                "theta": "-147.62198496",
                "gamma": "0.00004015",
                "vega": "80.50190804",
                "highPriceLimit": "20999.7",
                "lowPriceLimit": "5",
                "riskFreeInterest": "0.01791065"
            },
            {
                "symbol": "111000-C",
                "delta": 0
            },
            {
                "symbol": "112000-C",
                "markPrice": "3665",
                "bidIV": "0.44409037",
                "askIV": "0.4513222",
                "markIV": "0.44409037",
                "delta": "0.5145991",
                "theta": "-147.08196085",
                "gamma": "0.00004279",
                "vega": "82.9678838",
                "highPriceLimit": "23085.2",
                "lowPriceLimit": "5",
                "riskFreeInterest": "0.01791065"
            },
            {
                "symbol": "113000-C",
                "markPrice": "3179.9",
                "bidIV": "0.44247627",
                "askIV": "0.44428825",
                "markIV": "0.44247627",
                "delta": "0.47040219",
                "theta": "-145.32608884",
                "gamma": "0.00004313",
                "vega": "82.77627433",
                "highPriceLimit": "23061.2",
                "lowPriceLimit": "5",
                "riskFreeInterest": "0.01791065"
            },
            {
                "symbol": "114000-C",
                "markPrice": "2745",
                "bidIV": "0.43891847",
                "askIV": "0.44075489",
                "markIV": "0.43891847",
                "delta": "0.42828648",
                "theta": "-142.2509512",
                "gamma": "0.00004288",
                "vega": "81.67845687",
                "highPriceLimit": "22874.2",
                "lowPriceLimit": "5",
                "riskFreeInterest": "0.01791065"
            },
            {
                "symbol": "115000-C",
                "delta": 0
            }
        ],
        "251012": [
            {
                "symbol": "109000-C",
                "markPrice": "2936.5",
                "bidIV": "0.0000006",
                "askIV": "-0.00000001",
                "markIV": "0.4396",
                "delta": "0.92416309",
                "theta": "-237.45921326",
                "gamma": "0.00006841",
                "vega": "6.62015277",
                "highPriceLimit": "13004.1",
                "lowPriceLimit": "5",
                "riskFreeInterest": "0.02237871"
            },
            {
                "symbol": "110000-C",
                "markPrice": "1978.2",
                "bidIV": "0.0000006",
                "askIV": "-0.00000001",
                "markIV": "0.3641",
                "delta": "0.86915513",
                "theta": "-353.44875142",
                "gamma": "0.00010183",
                "vega": "9.85438391",
                "highPriceLimit": "12045.8",
                "lowPriceLimit": "5",
                "riskFreeInterest": "0.02237871"
            },
            {
                "symbol": "111000-C",
                "markPrice": "1120",
                "bidIV": "0.3176415",
                "askIV": "0.38352489",
                "markIV": "0.3176415",
                "delta": "0.72545737",
                "theta": "-432.04225382",
                "gamma": "0.00020506",
                "vega": "15.46175118",
                "highPriceLimit": "12176.2",
                "lowPriceLimit": "5",
                "riskFreeInterest": "0.02237871"
            },
            {
                "symbol": "112000-C",
                "markPrice": "505",
                "bidIV": "0.30115128",
                "askIV": "0.32010913",
                "markIV": "0.30115128",
                "delta": "0.47154786",
                "theta": "-456.97514815",
                "gamma": "0.00027616",
                "vega": "18.45850369",
                "highPriceLimit": "21647.6",
                "lowPriceLimit": "5",
                "riskFreeInterest": "0.02237871"
            },
            {
                "symbol": "113000-C",
                "markPrice": "160",
                "bidIV": "0.29624462",
                "askIV": "0.3110677",
                "markIV": "0.29624462",
                "delta": "0.20765933",
                "theta": "-321.35351625",
                "gamma": "0.00020332",
                "vega": "13.27701584",
                "highPriceLimit": "29904.7",
                "lowPriceLimit": "5",
                "riskFreeInterest": "0.02237871"
            },
            {
                "symbol": "114000-C",
                "markPrice": "55",
                "bidIV": "0.32132149",
                "askIV": "0.32831848",
                "markIV": "0.32132149",
                "delta": "0.08155117",
                "theta": "-181.12964985",
                "gamma": "0.00010011",
                "vega": "6.99697663",
                "highPriceLimit": "32392.3",
                "lowPriceLimit": "5",
                "riskFreeInterest": "0.02237871"
            },
            {
                "symbol": "115000-C",
                "markPrice": "25",
                "bidIV": "0.36813617",
                "askIV": "0.38079083",
                "markIV": "0.36813617",
                "delta": "0.0369045",
                "theta": "-111.71626531",
                "gamma": "0.00004646",
                "vega": "3.74329891",
                "highPriceLimit": "31622.9",
                "lowPriceLimit": "5",
                "riskFreeInterest": "0.02237871"
            }
        ],
        "251013": [
            {
                "symbol": "109000-C",
                "markPrice": "3298.9",
                "bidIV": "0.47698259",
                "askIV": "0.52533627",
                "markIV": "0.4836",
                "delta": "0.79461308",
                "theta": "-327.15550548",
                "gamma": "0.00007599",
                "vega": "21.24628435",
                "highPriceLimit": "13366.7",
                "lowPriceLimit": "5",
                "riskFreeInterest": "0.02062438"
            },
            {
                "symbol": "110000-C",
                "delta": 0
            },
            {
                "symbol": "111000-C",
                "markPrice": "1792.6",
                "bidIV": "0.42977333",
                "askIV": "0.45598269",
                "markIV": "0.4377",
                "delta": "0.61332405",
                "theta": "-389.06312937",
                "gamma": "0.00011568",
                "vega": "28.59214918",
                "highPriceLimit": "17366.6",
                "lowPriceLimit": "5",
                "riskFreeInterest": "0.02062438"
            },
            {
                "symbol": "112000-C",
                "markPrice": "1205",
                "bidIV": "0.42108715",
                "askIV": "0.4294765",
                "markIV": "0.42108715",
                "delta": "0.49261725",
                "theta": "-389.37942921",
                "gamma": "0.00012554",
                "vega": "29.79978986",
                "highPriceLimit": "21504.7",
                "lowPriceLimit": "5",
                "riskFreeInterest": "0.02062438"
            },
            {
                "symbol": "113000-C",
                "markPrice": "774.9",
                "bidIV": "0.41948974",
                "askIV": "0.42304516",
                "markIV": "0.41948974",
                "delta": "0.36633635",
                "theta": "-363.85700494",
                "gamma": "0.00011959",
                "vega": "28.11127788",
                "highPriceLimit": "24575.8",
                "lowPriceLimit": "5",
                "riskFreeInterest": "0.02062438"
            },
            {
                "symbol": "114000-C",
                "markPrice": "465",
                "bidIV": "0.40920019",
                "askIV": "0.42169213",
                "markIV": "0.4134",
                "delta": "0.25444417",
                "theta": "-305.86594956",
                "gamma": "0.00010334",
                "vega": "23.96274064",
                "highPriceLimit": "26715",
                "lowPriceLimit": "5",
                "riskFreeInterest": "0.02062438"
            },
            {
                "symbol": "115000-C",
                "markPrice": "295",
                "bidIV": "0.42908609",
                "askIV": "0.43168902",
                "markIV": "0.42908609",
                "delta": "0.17355143",
                "theta": "-253.31894922",
                "gamma": "0.00007975",
                "vega": "19.15688929",
                "highPriceLimit": "27409.6",
                "lowPriceLimit": "5",
                "riskFreeInterest": "0.02062438"
            }
        ],
        "251014": [
            {
                "symbol": "109000-C",
                "markPrice": "3758.2",
                "bidIV": "0.0000006",
                "askIV": "-0.00000001",
                "markIV": "0.535",
                "delta": "0.72464438",
                "theta": "-271.36833892",
                "gamma": "0.00007818",
                "vega": "31.68699972",
                "highPriceLimit": "14846.7",
                "lowPriceLimit": "5",
                "riskFreeInterest": "0.01989944"
            },
            {
                "symbol": "110000-C",
                "markPrice": "3017.4",
                "bidIV": "0.50350308",
                "askIV": "0.52933931",
                "markIV": "0.5157",
                "delta": "0.65859389",
                "theta": "-342.30086966",
                "gamma": "0.00007488",
                "vega": "34.82848408",
                "highPriceLimit": "16765.8",
                "lowPriceLimit": "5",
                "riskFreeInterest": "0.01989944"
            },
            {
                "symbol": "111000-C",
                "markPrice": "2354.9",
                "bidIV": "0.48747778",
                "askIV": "0.50906658",
                "markIV": "0.4996",
                "delta": "0.58195613",
                "theta": "-351.42428772",
                "gamma": "0.00008258",
                "vega": "37.05950297",
                "highPriceLimit": "19189.5",
                "lowPriceLimit": "5",
                "riskFreeInterest": "0.01989944"
            },
            {
                "symbol": "112000-C",
                "markPrice": "1773.3",
                "bidIV": "0.47802687",
                "askIV": "0.48595071",
                "markIV": "0.4842",
                "delta": "0.49753907",
                "theta": "-347.2892241",
                "gamma": "0.00008721",
                "vega": "37.86038305",
                "highPriceLimit": "21839.9",
                "lowPriceLimit": "5",
                "riskFreeInterest": "0.01989944"
            },
            {
                "symbol": "113000-C",
                "markPrice": "1295.4",
                "bidIV": "0.46775639",
                "askIV": "0.47860026",
                "markIV": "0.4733",
                "delta": "0.40969795",
                "theta": "-332.17697153",
                "gamma": "0.00008655",
                "vega": "36.88765502",
                "highPriceLimit": "23455.5",
                "lowPriceLimit": "5",
                "riskFreeInterest": "0.01989944"
            },
            {
                "symbol": "114000-C",
                "markPrice": "941.8",
                "bidIV": "0.46483636",
                "askIV": "0.47798097",
                "markIV": "0.4727",
                "delta": "0.32727369",
                "theta": "-307.3305915",
                "gamma": "0.00008067",
                "vega": "34.25602354",
                "highPriceLimit": "24589.1",
                "lowPriceLimit": "5",
                "riskFreeInterest": "0.01989944"
            },
            {
                "symbol": "115000-C",
                "markPrice": "666.3",
                "bidIV": "0.46448588",
                "askIV": "0.47605693",
                "markIV": "0.4732",
                "delta": "0.25281046",
                "theta": "-271.51092166",
                "gamma": "0.00007162",
                "vega": "30.33703874",
                "highPriceLimit": "25126.8",
                "lowPriceLimit": "5",
                "riskFreeInterest": "0.01989944"
            }
        ]
    },
    {
        "251017": [
            33,
            38,
            0,
            51,
            45,
            39,
            0
        ],
        "251024": [
            36,
            40,
            0,
            51,
            47,
            43,
            0
        ],
        "251012": [
            9,
            16,
            28,
            47,
            21,
            8,
            4
        ],
        "251013": [
            21,
            0,
            39,
            49,
            37,
            25,
            17
        ],
        "251014": [
            28,
            34,
            42,
            50,
            41,
            33,
            25
        ]
    },
    {
        "251017": [
            {
                "symbol": "109000-P",
                "markPrice": "1574.9",
                "bidIV": "0.50813198",
                "askIV": "0.51112592",
                "markIV": "0.51112592",
                "delta": "-0.32699603",
                "theta": "-226.98005254",
                "gamma": "0.00005096",
                "vega": "50.12713082",
                "highPriceLimit": "24019.6",
                "lowPriceLimit": "5",
                "riskFreeInterest": "0.01877188"
            },
            {
                "symbol": "110000-P",
                "markPrice": "1890",
                "bidIV": "0.49651384",
                "askIV": "0.499354",
                "markIV": "0.499354",
                "delta": "-0.37827233",
                "theta": "-233.70111978",
                "gamma": "0.00005496",
                "vega": "52.82353134",
                "highPriceLimit": "24116.8",
                "lowPriceLimit": "5",
                "riskFreeInterest": "0.01877188"
            },
            {
                "symbol": "111000-P",
                "delta": 0
            },
            {
                "symbol": "112000-P",
                "markPrice": "2694.4",
                "bidIV": "0.47434807",
                "askIV": "0.47976255",
                "markIV": "0.47875536",
                "delta": "-0.49296308",
                "theta": "-234.8878535",
                "gamma": "0.00006018",
                "vega": "55.41547633",
                "highPriceLimit": "23117.5",
                "lowPriceLimit": "5",
                "riskFreeInterest": "0.01877188"
            },
            {
                "symbol": "113000-P",
                "markPrice": "3228.2",
                "bidIV": "0.46498179",
                "askIV": "0.47772765",
                "markIV": "0.4765",
                "delta": "-0.55282244",
                "theta": "-230.07974696",
                "gamma": "0.00006039",
                "vega": "54.93749863",
                "highPriceLimit": "21240.2",
                "lowPriceLimit": "5",
                "riskFreeInterest": "0.01877188"
            },
            {
                "symbol": "114000-P",
                "markPrice": "3818.1",
                "bidIV": "0.0000006",
                "askIV": "1.86733246",
                "markIV": "0.4737",
                "delta": "-0.61168867",
                "theta": "-378.4158129",
                "gamma": "0.00003448",
                "vega": "53.23760821",
                "highPriceLimit": "19459",
                "lowPriceLimit": "5",
                "riskFreeInterest": "0.01877188"
            },
            {
                "symbol": "115000-P",
                "delta": 0
            }
        ],
        "251024": [
            {
                "symbol": "109000-P",
                "markPrice": "2429.9",
                "bidIV": "0.44261754",
                "askIV": "0.45354545",
                "markIV": "0.45354545",
                "delta": "-0.36045604",
                "theta": "-138.17331391",
                "gamma": "0.00004015",
                "vega": "77.87631334",
                "highPriceLimit": "23785.7",
                "lowPriceLimit": "5",
                "riskFreeInterest": "0.01791065"
            },
            {
                "symbol": "110000-P",
                "markPrice": "2790",
                "bidIV": "0.44361711",
                "askIV": "0.44672608",
                "markIV": "0.44672608",
                "delta": "-0.40088058",
                "theta": "-141.77588729",
                "gamma": "0.00004174",
                "vega": "80.42945695",
                "highPriceLimit": "24238.8",
                "lowPriceLimit": "5",
                "riskFreeInterest": "0.01791065"
            },
            {
                "symbol": "111000-P",
                "delta": 0
            },
            {
                "symbol": "112000-P",
                "markPrice": "3644.9",
                "bidIV": "0.43042004",
                "askIV": "0.43644607",
                "markIV": "0.43644607",
                "delta": "-0.48571713",
                "theta": "-142.3969623",
                "gamma": "0.0000442",
                "vega": "82.97026653",
                "highPriceLimit": "24359.9",
                "lowPriceLimit": "5",
                "riskFreeInterest": "0.01791065"
            },
            {
                "symbol": "113000-P",
                "markPrice": "4144.9",
                "bidIV": "0.42222977",
                "askIV": "0.43008566",
                "markIV": "0.43008566",
                "delta": "-0.53137874",
                "theta": "-139.6326176",
                "gamma": "0.00004485",
                "vega": "82.74792881",
                "highPriceLimit": "23016.5",
                "lowPriceLimit": "5",
                "riskFreeInterest": "0.01791065"
            },
            {
                "symbol": "114000-P",
                "markPrice": "4700",
                "bidIV": "0.41597128",
                "askIV": "0.42823792",
                "markIV": "0.42823792",
                "delta": "-0.5742706",
                "theta": "-136.35242938",
                "gamma": "0.00004463",
                "vega": "81.58054238",
                "highPriceLimit": "21848.1",
                "lowPriceLimit": "5",
                "riskFreeInterest": "0.01791065"
            },
            {
                "symbol": "115000-P",
                "delta": 0
            }
        ],
        "251012": [
            {
                "symbol": "109000-P",
                "markPrice": "99.9",
                "bidIV": "0.48121631",
                "askIV": "0.48753202",
                "markIV": "0.48121631",
                "delta": "-0.09487635",
                "theta": "-302.32586913",
                "gamma": "0.00007517",
                "vega": "7.8304341",
                "highPriceLimit": "30331.5",
                "lowPriceLimit": "5",
                "riskFreeInterest": "0.02237871"
            },
            {
                "symbol": "110000-P",
                "markPrice": "160",
                "bidIV": "0.40992856",
                "askIV": "0.4143554",
                "markIV": "0.40992856",
                "delta": "-0.1589654",
                "theta": "-369.08871298",
                "gamma": "0.00012676",
                "vega": "11.23568234",
                "highPriceLimit": "30269.5",
                "lowPriceLimit": "5",
                "riskFreeInterest": "0.02237871"
            },
            {
                "symbol": "111000-P",
                "markPrice": "304.9",
                "bidIV": "0.35227537",
                "askIV": "0.35540044",
                "markIV": "0.35227537",
                "delta": "-0.29404942",
                "theta": "-450.60083928",
                "gamma": "0.00020995",
                "vega": "15.977587",
                "highPriceLimit": "27268.6",
                "lowPriceLimit": "5",
                "riskFreeInterest": "0.02237871"
            },
            {
                "symbol": "112000-P",
                "markPrice": "614.9",
                "bidIV": "0.30197144",
                "askIV": "0.33175945",
                "markIV": "0.30197144",
                "delta": "-0.52836148",
                "theta": "-466.15552259",
                "gamma": "0.00027073",
                "vega": "18.45880338",
                "highPriceLimit": "19612.2",
                "lowPriceLimit": "5",
                "riskFreeInterest": "0.02237871"
            },
            {
                "symbol": "113000-P",
                "markPrice": "1255.2",
                "bidIV": "0.23167133",
                "askIV": "0.31600952",
                "markIV": "0.2666",
                "delta": "-0.81765388",
                "theta": "-267.7696565",
                "gamma": "0.00020831",
                "vega": "12.26747829",
                "highPriceLimit": "11322.8",
                "lowPriceLimit": "5",
                "riskFreeInterest": "0.02237871"
            },
            {
                "symbol": "114000-P",
                "markPrice": "2149.1",
                "bidIV": "0.0000006",
                "askIV": "9.9999994",
                "markIV": "0.2995",
                "delta": "-0.93283842",
                "theta": "-384.62098865",
                "gamma": "0.00003504",
                "vega": "6.03262885",
                "highPriceLimit": "12218.9",
                "lowPriceLimit": "5",
                "riskFreeInterest": "0.02237871"
            },
            {
                "symbol": "115000-P",
                "markPrice": "3135.4",
                "bidIV": "0.0000006",
                "askIV": "-0.00000001",
                "markIV": "0.3546",
                "delta": "-0.96862291",
                "theta": "-117.47669166",
                "gamma": "0.00003383",
                "vega": "3.27550881",
                "highPriceLimit": "13204.6",
                "lowPriceLimit": "5",
                "riskFreeInterest": "0.02237871"
            }
        ],
        "251013": [
            {
                "symbol": "109000-P",
                "markPrice": "440",
                "bidIV": "0.49093902",
                "askIV": "0.49326479",
                "markIV": "0.49093902",
                "delta": "-0.2089775",
                "theta": "-324.54588404",
                "gamma": "0.00007818",
                "vega": "21.46459166",
                "highPriceLimit": "26860.6",
                "lowPriceLimit": "5",
                "riskFreeInterest": "0.02062438"
            },
            {
                "symbol": "110000-P",
                "delta": 0
            },
            {
                "symbol": "111000-P",
                "markPrice": "909.9",
                "bidIV": "0.44039011",
                "askIV": "0.44737816",
                "markIV": "0.44039011",
                "delta": "-0.38728086",
                "theta": "-390.12400435",
                "gamma": "0.00011547",
                "vega": "28.60512773",
                "highPriceLimit": "24294",
                "lowPriceLimit": "5",
                "riskFreeInterest": "0.02062438"
            },
            {
                "symbol": "112000-P",
                "markPrice": "1305.4",
                "bidIV": "0.40682673",
                "askIV": "0.43534994",
                "markIV": "0.4204",
                "delta": "-0.50741313",
                "theta": "-385.53941482",
                "gamma": "0.00012679",
                "vega": "29.79974776",
                "highPriceLimit": "21146.5",
                "lowPriceLimit": "5",
                "riskFreeInterest": "0.02062438"
            },
            {
                "symbol": "113000-P",
                "markPrice": "1864.4",
                "bidIV": "0.3945744",
                "askIV": "0.42490602",
                "markIV": "0.4087",
                "delta": "-0.63732583",
                "theta": "-352.70759476",
                "gamma": "0.00012254",
                "vega": "28.01650633",
                "highPriceLimit": "16470.4",
                "lowPriceLimit": "5",
                "riskFreeInterest": "0.02062438"
            },
            {
                "symbol": "114000-P",
                "markPrice": "2567.3",
                "bidIV": "0.28017521",
                "askIV": "0.47326088",
                "markIV": "0.4134",
                "delta": "-0.74555583",
                "theta": "-277.35295884",
                "gamma": "0.00011396",
                "vega": "23.96274064",
                "highPriceLimit": "12816.1",
                "lowPriceLimit": "5",
                "riskFreeInterest": "0.02062438"
            },
            {
                "symbol": "115000-P",
                "markPrice": "3378.4",
                "bidIV": "0.0000006",
                "askIV": "-0.00000001",
                "markIV": "0.4192",
                "delta": "-0.83224344",
                "theta": "-259.16737608",
                "gamma": "0.00007463",
                "vega": "18.7448404",
                "highPriceLimit": "13448.2",
                "lowPriceLimit": "5",
                "riskFreeInterest": "0.02062438"
            }
        ],
        "251014": [
            {
                "symbol": "109000-P",
                "markPrice": "900",
                "bidIV": "0.54082453",
                "askIV": "0.54239571",
                "markIV": "0.54082453",
                "delta": "-0.27734024",
                "theta": "-327.76635668",
                "gamma": "0.00006519",
                "vega": "31.79875716",
                "highPriceLimit": "25039.1",
                "lowPriceLimit": "5",
                "riskFreeInterest": "0.01989944"
            },
            {
                "symbol": "110000-P",
                "markPrice": "1140.4",
                "bidIV": "0.50549448",
                "askIV": "0.5169946",
                "markIV": "0.5157",
                "delta": "-0.34140611",
                "theta": "-338.86960776",
                "gamma": "0.00007564",
                "vega": "34.82848408",
                "highPriceLimit": "24720.1",
                "lowPriceLimit": "5",
                "riskFreeInterest": "0.01989944"
            },
            {
                "symbol": "111000-P",
                "markPrice": "1477.8",
                "bidIV": "0.49208462",
                "askIV": "0.50287962",
                "markIV": "0.4996",
                "delta": "-0.41804373",
                "theta": "-350.86781756",
                "gamma": "0.00008271",
                "vega": "37.05941868",
                "highPriceLimit": "23710.4",
                "lowPriceLimit": "5",
                "riskFreeInterest": "0.01989944"
            },
            {
                "symbol": "112000-P",
                "markPrice": "1896.1",
                "bidIV": "0.46936393",
                "askIV": "0.4878521",
                "markIV": "0.4842",
                "delta": "-0.50246093",
                "theta": "-344.85326104",
                "gamma": "0.00008783",
                "vega": "37.86038305",
                "highPriceLimit": "21932",
                "lowPriceLimit": "5",
                "riskFreeInterest": "0.01989944"
            },
            {
                "symbol": "113000-P",
                "markPrice": "2417.5",
                "bidIV": "0.45767784",
                "askIV": "0.48479795",
                "markIV": "0.4733",
                "delta": "-0.59041433",
                "theta": "-330.79056927",
                "gamma": "0.0000869",
                "vega": "36.88463191",
                "highPriceLimit": "18911.5",
                "lowPriceLimit": "5",
                "riskFreeInterest": "0.01989944"
            },
            {
                "symbol": "114000-P",
                "markPrice": "3057.7",
                "bidIV": "0.40349483",
                "askIV": "0.50523281",
                "markIV": "0.4727",
                "delta": "-0.67257177",
                "theta": "-296.28083956",
                "gamma": "0.00008372",
                "vega": "34.26309783",
                "highPriceLimit": "16244",
                "lowPriceLimit": "5",
                "riskFreeInterest": "0.01989944"
            },
            {
                "symbol": "115000-P",
                "markPrice": "3788.6",
                "bidIV": "0.0000006",
                "askIV": "-0.00000001",
                "markIV": "0.4732",
                "delta": "-0.74719004",
                "theta": "-259.80753651",
                "gamma": "0.00007485",
                "vega": "30.3369402",
                "highPriceLimit": "13969.2",
                "lowPriceLimit": "5",
                "riskFreeInterest": "0.01989944"
            }
        ]
    }
]